evg/__init__.py
evg/core.py
evg-2.8.0.dist-info/METADATA
evg-2.8.0.dist-info/WHEEL
evg-2.8.0.dist-info/top_level.txt
evg-2.8.0.dist-info/RECORD
