Metadata-Version: 2.1
Name: evg
Version: 2.8.0
Summary: Discord translator & translation of Discord functions/interactions
Home-page: https://github.com/IceOne-i/evg
Author: Nikita Belan
Author-email: nikitabelan9@gmail.com
License: MIT
